password_compat.py
password_compat-0.2.2.dist-info/WHEEL
password_compat-0.2.2.dist-info/METADATA
password_compat-0.2.2.dist-info/RECORD
